{
  "movies": [
    {
      "id": "1",
      "title": "Godzilla",
      "rating": "4.9"
    },
    {
      "title": "Avedgars",
      "rating": "4.7",
      "id": "2"
    },
    {
      "title": "Supermun",
      "rating": "4.8",
      "id": "3"
    },
    {
      "title": "Butman",
      "rating": "4.6",
      "id": "4"
    },
    {
      "id": "fc32",
      "title": "Avengers",
      "rating": "4.0"
    },
    {
      "id": "f7f7",
      "title": "Star wars",
      "rating": "5.0"
    },
    {
      "id": "b6ff",
      "title": "Kalle Anka",
      "rating": "4.9"
    },
    {
      "id": "d7ae",
      "title": "Kalle Anka",
      "rating": "4.9"
    },
    {
      "title": "Kalle Apa",
      "rating": "4",
      "id": "fc7d"
    },
    {
      "id": "79c3",
      "title": "Kalle Anka",
      "rating": "4"
    },
    {
      "id": "abe0",
      "title": "Mupparna",
      "rating": "7"
    },
    {
      "id": "20bf",
      "title": "Mupparna",
      "rating": "7"
    }
  ]
}